act/__init__.py
act/act.py
act/action.py
act/action_covid.py
act/action_ensure_zone1_flow_temperature_is_correct.py
act/action_manage_power_state_for_space_heating.py
act/action_manage_tank_temperature.py
act/action_octopus_go.py
act/action_stop_forcing_hot_water.py
act/action_turn_off_power.py
act/action_turn_on_power.py
act/alter_setting.py
act/device_infos.py
act/dwell.py
act/effective_temperature.py
act/emoncms.py
act/last_time_stamp.py
act/log4j.properties
act/midpoint_temp.py
act/occupant_comes_home.py
act/predicate.py
act/schedule.py
act/simple_checks.py
act/state_change.py
act/target_water_temperature.py
act/temperature_thresholds.py
act/time_based_criteria.py
heatpump_act-0.1.1.dist-info/WHEEL
heatpump_act-0.1.1.dist-info/METADATA
heatpump_act-0.1.1.dist-info/RECORD
