Metadata-Version: 2.1
Name: heatpump-act
Version: 0.1.1
Summary: Scripts to act on a heatpump
Home-page: https://github.com/MyForest/heatpump-act
License: MIT
Author: David Bowen
Author-email: david@myforest.com
Requires-Python: >=3.6.2
Classifier: License :: OSI Approved :: MIT License
Classifier: Programming Language :: Python :: 3
Classifier: Programming Language :: Python :: 3.10
Classifier: Programming Language :: Python :: 3.7
Classifier: Programming Language :: Python :: 3.8
Classifier: Programming Language :: Python :: 3.9
Requires-Dist: croniter
Requires-Dist: python-crontab
Requires-Dist: python-dotenv
Requires-Dist: pytz
Requires-Dist: structlog
Requires-Dist: tqdm
Requires-Dist: typer
Requires-Dist: urllib3
Project-URL: Repository, https://github.com/MyForest/heatpump-act
